{
	"backtrace" : 4,
	"backtraceGraph" : 
	{
		"commands" : 
		[
			"add_custom_target",
			"include",
			"generate_messages",
			"add_dependencies"
		],
		"files" : 
		[
			"/home/tor/catkin_ws/build/aruco_ros/aruco_msgs/cmake/aruco_msgs-genmsg.cmake",
			"/opt/ros/noetic/share/genmsg/cmake/genmsg-extras.cmake",
			"aruco_ros/aruco_msgs/CMakeLists.txt"
		],
		"nodes" : 
		[
			{
				"file" : 2
			},
			{
				"command" : 2,
				"file" : 2,
				"line" : 10,
				"parent" : 0
			},
			{
				"command" : 1,
				"file" : 1,
				"line" : 307,
				"parent" : 1
			},
			{
				"file" : 0,
				"parent" : 2
			},
			{
				"command" : 0,
				"file" : 0,
				"line" : 98,
				"parent" : 3
			},
			{
				"command" : 3,
				"file" : 0,
				"line" : 105,
				"parent" : 3
			},
			{
				"command" : 3,
				"file" : 0,
				"line" : 263,
				"parent" : 3
			},
			{
				"command" : 3,
				"file" : 0,
				"line" : 107,
				"parent" : 3
			},
			{
				"command" : 3,
				"file" : 0,
				"line" : 266,
				"parent" : 3
			}
		]
	},
	"dependencies" : 
	[
		{
			"backtrace" : 5,
			"id" : "_aruco_msgs_generate_messages_check_deps_Marker::@d70c884c85295080cd2f"
		},
		{
			"backtrace" : 6,
			"id" : "std_msgs_generate_messages_eus::@d70c884c85295080cd2f"
		},
		{
			"backtrace" : 7,
			"id" : "_aruco_msgs_generate_messages_check_deps_MarkerArray::@d70c884c85295080cd2f"
		},
		{
			"backtrace" : 8,
			"id" : "geometry_msgs_generate_messages_eus::@d70c884c85295080cd2f"
		}
	],
	"id" : "aruco_msgs_generate_messages_eus::@d70c884c85295080cd2f",
	"name" : "aruco_msgs_generate_messages_eus",
	"paths" : 
	{
		"build" : "aruco_ros/aruco_msgs",
		"source" : "aruco_ros/aruco_msgs"
	},
	"sourceGroups" : 
	[
		{
			"name" : "",
			"sourceIndexes" : 
			[
				0
			]
		},
		{
			"name" : "CMake Rules",
			"sourceIndexes" : 
			[
				1,
				2,
				3,
				4
			]
		}
	],
	"sources" : 
	[
		{
			"backtrace" : 4,
			"isGenerated" : true,
			"path" : "/home/tor/catkin_ws/build/aruco_ros/aruco_msgs/CMakeFiles/aruco_msgs_generate_messages_eus",
			"sourceGroupIndex" : 0
		},
		{
			"backtrace" : 0,
			"isGenerated" : true,
			"path" : "/home/tor/catkin_ws/build/aruco_ros/aruco_msgs/CMakeFiles/aruco_msgs_generate_messages_eus.rule",
			"sourceGroupIndex" : 1
		},
		{
			"backtrace" : 0,
			"isGenerated" : true,
			"path" : "/home/tor/catkin_ws/devel/share/roseus/ros/aruco_msgs/msg/Marker.l.rule",
			"sourceGroupIndex" : 1
		},
		{
			"backtrace" : 0,
			"isGenerated" : true,
			"path" : "/home/tor/catkin_ws/devel/share/roseus/ros/aruco_msgs/msg/MarkerArray.l.rule",
			"sourceGroupIndex" : 1
		},
		{
			"backtrace" : 0,
			"isGenerated" : true,
			"path" : "/home/tor/catkin_ws/devel/share/roseus/ros/aruco_msgs/manifest.l.rule",
			"sourceGroupIndex" : 1
		}
	],
	"type" : "UTILITY"
}
